{
    "name": "Arm",
    "fields": [
        {
            "fieldName": "name",
            "fieldType": "String",
            "fieldValidateRules": [
                "required"
            ]
        }
    ],
    "relationships": [
        {
            "relationshipType": "many-to-many",
            "otherEntityName": "armIp",
            "otherEntityRelationshipName": "arm",
            "relationshipName": "armIp",
            "otherEntityField": "ip",
            "ownerSide": true
        },
        {
            "relationshipType": "one-to-many",
            "otherEntityName": "racfUser",
            "otherEntityRelationshipName": "arm",
            "relationshipName": "name"
        }
    ],
    "changelogDate": "20190604132605",
    "entityTableName": "arm",
    "dto": "mapstruct",
    "pagination": "pagination",
    "service": "serviceImpl",
    "jpaMetamodelFiltering": false,
    "fluentMethods": true,
    "clientRootFolder": "",
    "applications": "*"
}