{
    "name": "ZosSystem",
    "fields": [
        {
            "fieldName": "name",
            "fieldType": "String",
            "fieldValidateRules": [
                "required"
            ]
        },
        {
            "fieldName": "ip",
            "fieldType": "String",
            "fieldValidateRules": [
                "maxlength"
            ],
            "fieldValidateRulesMaxlength": 39
        }
    ],
    "relationships": [
        {
            "relationshipType": "many-to-many",
            "otherEntityName": "racfUser",
            "otherEntityRelationshipName": "system",
            "relationshipName": "name",
            "otherEntityField": "id",
            "ownerSide": false
        }
    ],
    "changelogDate": "20190603145913",
    "entityTableName": "zos_system",
    "dto": "mapstruct",
    "pagination": "pagination",
    "service": "serviceImpl",
    "jpaMetamodelFiltering": false,
    "fluentMethods": true,
    "clientRootFolder": "",
    "applications": "*"
}